pisces/__init__.py
pisces/canonical_isobar.py
pisces/config.py
pisces/constants.py
pisces/construct_junction_utils.py
pisces/construct_proteome.py
pisces/construct_proteome_utils.py
pisces/contaminants.py
pisces/create_report.py
pisces/custom_logo.py
pisces/delta_scores.py
pisces/download_swissprot.py
pisces/execute_casa.py
pisces/fdr_estimation.py
pisces/format_exhaustive.py
pisces/inspire.py
pisces/isobars.py
pisces/merge_ids.py
pisces/permute.py
pisces/plot_utils.py
pisces/preprocess.py
pisces/proteome_utils.py
pisces/quantify.py
pisces/remap.py
pisces/run.py
pisces/spectral_files.py
pisces/splicing_utils.py
pisces/translate_genome.py
pisces/utils.py
pisces/write_configs.py
pisces/report/__init__.py
pisces/report/qc_report_template.py
pisces/report/report_template.py
pisces_ms-0.4.dist-info/METADATA
pisces_ms-0.4.dist-info/WHEEL
pisces_ms-0.4.dist-info/entry_points.txt
pisces_ms-0.4.dist-info/top_level.txt
pisces_ms-0.4.dist-info/RECORD
