Metadata-Version: 2.4
Name: pisces-ms
Version: 0.4
Summary: Managing assignment of spliced peptides.
Author: John Cormican, Juliane Liepe
Author-email: juliane.liepe@mpinat.mpg.de
Project-URL: Homepage, https://github.com/QuantSysBio/inSPIRE
Project-URL: Tracker, https://github.com/QuantSysBio/inSPIRE/issues
Requires-Python: >=3.11
Requires-Dist: inspirems==3.0rc3
Requires-Dist: regex==2024.11.6
Requires-Dist: suffix-tree==0.1.2
Dynamic: author
Dynamic: author-email
Dynamic: description
Dynamic: description-content-type
Dynamic: project-url
Dynamic: requires-dist
Dynamic: requires-python
Dynamic: summary
